AlmacenBebidasAlba/Agua.py
AlmacenBebidasAlba/Almacen.py
AlmacenBebidasAlba/Bebida.py
AlmacenBebidasAlba/BebidaConGas.py
AlmacenBebidasAlba/__init__.py
AlmacenBebidasAlba/Clases/Agua.py
AlmacenBebidasAlba/Clases/Bebida.py
AlmacenBebidasAlba/Clases/BebidaConGas.py
AlmacenBebidasAlba/Clases/__init__.py
AlmacenBebidasAlba1-1.1.5.dist-info/METADATA
AlmacenBebidasAlba1-1.1.5.dist-info/WHEEL
AlmacenBebidasAlba1-1.1.5.dist-info/top_level.txt
AlmacenBebidasAlba1-1.1.5.dist-info/RECORD
